algorename/__init__.py
algorename/main.py
algorithms/__init__.py
algorithms/example.py
algorithms/example2.py
tests/__init__.py
tests/test_algorithms_example.py
algorename-1.6.dist-info/LICENSE
algorename-1.6.dist-info/METADATA
algorename-1.6.dist-info/WHEEL
algorename-1.6.dist-info/entry_points.txt
algorename-1.6.dist-info/top_level.txt
algorename-1.6.dist-info/RECORD
