Metadata-Version: 2.1
Name: algorename
Version: 1.6
Summary: A utility to change file names based on algorithms.
Author: Mario Nascimento
Author-email: mario@whitehathacking.tech
License-File: LICENSE
Requires-Dist: python-dotenv
Requires-Dist: pytest
